bitn.py
bitn-0.0.45.dist-info/METADATA
bitn-0.0.45.dist-info/WHEEL
bitn-0.0.45.dist-info/top_level.txt
bitn-0.0.45.dist-info/RECORD
