Metadata-Version: 2.1
Name: bitn
Version: 0.0.45
Summary: a better bitslicer9k
Home-page: https://github.com/futzu/bitn
Author: fu-corp
Author-email: spam@futzu.com
License: UNKNOWN
Platform: all
Classifier: License :: OSI Approved :: MIT License
Classifier: Operating System :: OS Independent
Classifier: Programming Language :: Python :: Implementation :: CPython
Classifier: Programming Language :: Python :: Implementation :: PyPy
Requires-Python: >=3.6
